pyrish/__init__.py
pyrish/_globals.py
pyrish/exceptions.py
pyrish/itertools.py
pyrish/operator.py
pyrish/platform.py
pyrish/types.py
pyrish-0.4.0.dist-info/DESCRIPTION.rst
pyrish-0.4.0.dist-info/METADATA
pyrish-0.4.0.dist-info/RECORD
pyrish-0.4.0.dist-info/WHEEL
pyrish-0.4.0.dist-info/metadata.json
pyrish-0.4.0.dist-info/top_level.txt
