Metadata-Version: 2.0
Name: pyrish
Version: 0.4.0
Summary: A growing collection of code and utility classes.
Home-page: https://github.com/dhiatn/pyrish
Author: Dhia Abbassi
Author-email: contact@dhia.io
License: MIT license
Keywords: pyrish
Platform: UNKNOWN
Classifier: Development Status :: 4 - Beta
Classifier: Intended Audience :: Developers
Classifier: License :: OSI Approved :: MIT License
Classifier: Natural Language :: English
Classifier: Programming Language :: Python :: 3.6
Requires-Dist: humanfriendly (==4.8)
Requires-Dist: psutil (==5.4.3)
